pytorch_cpr/__init__.py
pytorch_cpr/adamcpr.py
pytorch_cpr/group_parameter.py
pytorch_cpr-0.3.1.dist-info/METADATA
pytorch_cpr-0.3.1.dist-info/WHEEL
pytorch_cpr-0.3.1.dist-info/licenses/LICENSE
pytorch_cpr-0.3.1.dist-info/RECORD
