Metadata-Version: 2.3
Name: pytorch-cpr
Version: 0.3.1
Summary: Constrained Parameter Regularization for PyTorch
Project-URL: Homepage, https://github.com/automl/CPR
Author-email: Jörg Franke <frankej@cs.uni-freiburg.de>
Classifier: License :: OSI Approved :: Apache Software License
Classifier: Operating System :: OS Independent
Classifier: Programming Language :: Python :: 3
Requires-Python: >=3.10
Provides-Extra: full
Requires-Dist: pytorch>=2.3.1; extra == 'full'
